{
    "user": [
        {
            "@lastname": "Doe", 
            "birth-date": {
                "#text": "1978-01-01"
            }, 
            "@firstname": "John", 
            "office": {
                "#text": "1st Ave"
            }
        }, 
        {
            "@lastname": "Foo", 
            "birth-date": {
                "#text": "1970-01-01"
            }, 
            "@firstname": "Jane", 
            "office": {
                "#text": "2nd Ave"
            }
        }
    ]
}